gym_fantasy_football_auction
